pinkopy/__init__.py
pinkopy/agents.py
pinkopy/base_session.py
pinkopy/clients.py
pinkopy/commvault.py
pinkopy/exceptions.py
pinkopy/jobs.py
pinkopy/subclients.py
tests/__init__.py
tests/pinkopy/__init__.py
tests/pinkopy/test_agents.py
tests/pinkopy/test_base_session.py
tests/pinkopy/test_commvault.py
tests/pinkopy/test_exceptions.py
tests/pinkopy/test_helper.py
commvault_client-2.3.0.dist-info/LICENSE
commvault_client-2.3.0.dist-info/METADATA
commvault_client-2.3.0.dist-info/WHEEL
commvault_client-2.3.0.dist-info/top_level.txt
commvault_client-2.3.0.dist-info/RECORD
