Metadata-Version: 2.1
Name: commvault-client
Version: 2.3.0
Summary: Python wrapper for Commvault api
Home-page: https://github.com/ronaldodduarte/pinkopy
Author: Herkermer Sherwood
Author-email: theherk@gmail.com
License: MIT
Platform: all
Classifier: Development Status :: 4 - Beta
Classifier: License :: Other/Proprietary License
Classifier: License :: OSI Approved :: MIT License
Classifier: Environment :: Console
Classifier: Intended Audience :: Developers
Classifier: Intended Audience :: System Administrators
Classifier: Operating System :: MacOS :: MacOS X
Classifier: Operating System :: Unix
Classifier: Operating System :: POSIX
Classifier: Programming Language :: Python :: 3.2
Classifier: Programming Language :: Python :: 3.3
Classifier: Programming Language :: Python :: 3.4
Classifier: Programming Language :: Python :: 3.5
Classifier: Programming Language :: Python :: 3.8
Classifier: Topic :: Utilities
Requires-Dist: cachetools (>=1.1.5)
Requires-Dist: requests (>=2.7.0)
Requires-Dist: xmltodict (>=0.9.2)
